alphalens/__init__.py
alphalens/_version.py
alphalens/performance.py
alphalens/plotting.py
alphalens/tears.py
alphalens/utils.py
alphalens/examples/event_study.ipynb
alphalens/examples/intraday_factor.ipynb
alphalens/examples/overview.ipynb
alphalens/examples/pyfolio_integration.ipynb
alphalens_cn-0.4.8.dist-info/LICENSE
alphalens_cn-0.4.8.dist-info/METADATA
alphalens_cn-0.4.8.dist-info/WHEEL
alphalens_cn-0.4.8.dist-info/top_level.txt
alphalens_cn-0.4.8.dist-info/RECORD
