Metadata-Version: 2.1
Name: alphalens-cn
Version: 0.4.8
Summary: Performance analysis of predictive (alpha) stock factors
Author: gquant
Maintainer: gquant
License:                                  Apache License
Project-URL: repository, https://gitee.com/goldenquant/alphalens-reloaded
Classifier: Development Status :: 5 - Production/Stable
Classifier: License :: OSI Approved :: Apache Software License
Classifier: Natural Language :: English
Classifier: Programming Language :: Python
Classifier: Programming Language :: Python :: 3.8
Classifier: Programming Language :: Python :: 3.9
Classifier: Programming Language :: Python :: 3.10
Classifier: Programming Language :: Python :: 3.11
Classifier: Programming Language :: Python :: 3.12
Classifier: Operating System :: OS Independent
Classifier: Intended Audience :: Science/Research
Classifier: Topic :: Office/Business :: Financial :: Investment
Classifier: Topic :: Scientific/Engineering :: Information Analysis
Requires-Python: >=3.8
License-File: LICENSE
Requires-Dist: numpy>=1.20.0; python_version == "3.8"
Requires-Dist: numpy>=1.23.5; python_version < "3.12"
Requires-Dist: numpy>=1.26.0; python_version >= "3.12"
Requires-Dist: pandas<3.0,>=1.3.0
Requires-Dist: matplotlib>=1.4.0
Requires-Dist: scipy>=0.14.0
Requires-Dist: seaborn>=0.6.0
Requires-Dist: statsmodels>=0.6.1
Requires-Dist: IPython>=3.2.3
Requires-Dist: empyrical-reloaded>=0.5.7
Provides-Extra: test
Requires-Dist: tox>=2.3.1; extra == "test"
Requires-Dist: coverage>=4.0.3; extra == "test"
Requires-Dist: coveralls==3.0.1; extra == "test"
Requires-Dist: pytest>=6.2; extra == "test"
Requires-Dist: pytest-xdist>=2.5.0; extra == "test"
Requires-Dist: pytest-cov>=2.12; extra == "test"
Requires-Dist: parameterized>=0.6.1; extra == "test"
Requires-Dist: flake8>=3.9.1; extra == "test"
Requires-Dist: black; extra == "test"
Provides-Extra: dev
Requires-Dist: flake8>=3.9.1; extra == "dev"
Requires-Dist: black; extra == "dev"
Requires-Dist: pre-commit>=2.12.1; extra == "dev"
Provides-Extra: docs
Requires-Dist: Cython; extra == "docs"
Requires-Dist: Sphinx>=1.3.2; extra == "docs"
Requires-Dist: numpydoc>=0.5.0; extra == "docs"
Requires-Dist: sphinx-autobuild>=0.6.0; extra == "docs"
Requires-Dist: pydata-sphinx-theme; extra == "docs"
Requires-Dist: sphinx-markdown-tables; extra == "docs"
Requires-Dist: sphinx_copybutton; extra == "docs"
Requires-Dist: m2r2; extra == "docs"
